micropython_htu31d/__init__.py
micropython_htu31d/htu31d.py
micropython_htu31d-0.1.2.dist-info/LICENSE
micropython_htu31d-0.1.2.dist-info/METADATA
micropython_htu31d-0.1.2.dist-info/WHEEL
micropython_htu31d-0.1.2.dist-info/top_level.txt
micropython_htu31d-0.1.2.dist-info/RECORD
