Metadata-Version: 2.1
Name: micropython-htu31d
Version: 0.1.2
Summary: MicroPython library for TE HTU31D temperature and humidity sensors
Author-email: JDM <xxyx@mailmeto.mozmail.com>
License: MIT
Project-URL: Homepage, https://github.com/jposada202020/MicroPython_HTU31D
Keywords: sensor,micropython,htu31d,humidity,temperature,TE,htu31d,sensor,driver,micropython
Classifier: Intended Audience :: Developers
Classifier: Topic :: Software Development :: Libraries
Classifier: Topic :: Software Development :: Embedded Systems
Classifier: Topic :: System :: Hardware
Classifier: License :: OSI Approved :: MIT License
Classifier: Programming Language :: Python :: Implementation :: MicroPython
License-File: LICENSE
